tag_api/__init__.py
tag_api/client.py
tag_api/models.py
tag_api/util/__init__.py
tag_api/util/base/__init__.py
tag_api/util/base/accepted_http_methods.py
tag_api/util/base/decorators.py
tag_api/util/base/document_types.py
tag_api/util/base/excpetions.py
tag_api/util/base/payment_schemes.py
tag_api/util/contracts/__init__.py
tag_api/util/contracts/account_types.py
tag_api/util/contracts/contract_effect_strategies.py
tag_api/util/contracts/contract_effect_types.py
tag_api/util/contracts/division_methods.py
tag_api/util/contracts/warranty_types.py
python_tag_api-0.1.3.dist-info/LICENSE.txt
python_tag_api-0.1.3.dist-info/METADATA
python_tag_api-0.1.3.dist-info/WHEEL
python_tag_api-0.1.3.dist-info/top_level.txt
python_tag_api-0.1.3.dist-info/RECORD
