Metadata-Version: 2.1
Name: python-tag-api
Version: 0.1.3
Summary: Python wrapper for the TAG IMF API
Home-page: https://github.com/bordax/python-tag-api
Author: Rafael Bordin
Author-email: rafael.bordin@live.com
License: MIT
Platform: UNKNOWN
Classifier: Programming Language :: Python :: 3
Classifier: License :: OSI Approved :: MIT License
Classifier: Operating System :: OS Independent
Classifier: Development Status :: 2 - Pre-Alpha
Classifier: Intended Audience :: Developers
Requires-Python: >=3.8
License-File: LICENSE.txt
Requires-Dist: requests (>2.25)
